netbox_dns/__init__.py
netbox_dns/apps.py
netbox_dns/filters.py
netbox_dns/navigation.py
netbox_dns/template_content.py
netbox_dns/urls.py
netbox_dns/api/field_serializers.py
netbox_dns/api/nested_serializers.py
netbox_dns/api/serializers.py
netbox_dns/api/urls.py
netbox_dns/api/views.py
netbox_dns/api/serializers_/__init__.py
netbox_dns/api/serializers_/dnssec_key_template.py
netbox_dns/api/serializers_/dnssec_policy.py
netbox_dns/api/serializers_/nameserver.py
netbox_dns/api/serializers_/prefix.py
netbox_dns/api/serializers_/record.py
netbox_dns/api/serializers_/record_template.py
netbox_dns/api/serializers_/registrar.py
netbox_dns/api/serializers_/registration_contact.py
netbox_dns/api/serializers_/view.py
netbox_dns/api/serializers_/zone.py
netbox_dns/api/serializers_/zone_template.py
netbox_dns/choices/__init__.py
netbox_dns/choices/dnssec_key_template.py
netbox_dns/choices/dnssec_policy.py
netbox_dns/choices/record.py
netbox_dns/choices/utilities.py
netbox_dns/choices/zone.py
netbox_dns/fields/__init__.py
netbox_dns/fields/address.py
netbox_dns/fields/choice_array.py
netbox_dns/fields/ipam.py
netbox_dns/fields/network.py
netbox_dns/fields/rfc2317.py
netbox_dns/fields/timeperiod.py
netbox_dns/filtersets/__init__.py
netbox_dns/filtersets/dnssec_key_template.py
netbox_dns/filtersets/dnssec_policy.py
netbox_dns/filtersets/nameserver.py
netbox_dns/filtersets/record.py
netbox_dns/filtersets/record_template.py
netbox_dns/filtersets/registrar.py
netbox_dns/filtersets/registration_contact.py
netbox_dns/filtersets/view.py
netbox_dns/filtersets/zone.py
netbox_dns/filtersets/zone_template.py
netbox_dns/forms/__init__.py
netbox_dns/forms/dnssec_key_template.py
netbox_dns/forms/dnssec_policy.py
netbox_dns/forms/nameserver.py
netbox_dns/forms/record.py
netbox_dns/forms/record_template.py
netbox_dns/forms/registrar.py
netbox_dns/forms/registration_contact.py
netbox_dns/forms/view.py
netbox_dns/forms/zone.py
netbox_dns/forms/zone_template.py
netbox_dns/graphql/__init__.py
netbox_plugin_dns-1.5.1.dist-info/licenses/LICENSE
netbox_plugin_dns-1.5.1.dist-info/METADATA
netbox_plugin_dns-1.5.1.dist-info/WHEEL
netbox_plugin_dns-1.5.1.dist-info/top_level.txt
netbox_plugin_dns-1.5.1.dist-info/RECORD
