Metadata-Version: 2.4
Name: netbox-plugin-dns
Version: 1.5.1
Summary: NetBox DNS is a NetBox plugin for managing DNS data.
Author-email: Peter Eckel <pete@netbox-dns.org>
Project-URL: Homepage, https://github.com/peteeckel/netbox-plugin-dns
Project-URL: Documentation, https://github.com/peteeckel/netbox-plugin-dns/blob/main/docs/using_netbox_dns.md
Project-URL: Repository, https://github.com/peteeckel/netbox-plugin-dns
Project-URL: Issues, https://github.com/peteeckel/netbox-plugin-dns/issues
Keywords: netbox,netbox-plugin,dns
Classifier: Development Status :: 5 - Production/Stable
Classifier: Programming Language :: Python :: 3 :: Only
Classifier: Programming Language :: Python :: 3.12
Classifier: Programming Language :: Python :: 3.13
Classifier: Programming Language :: Python :: 3.14
Requires-Python: >=3.12
License-File: LICENSE
Requires-Dist: dnspython
Dynamic: license-file
